collective.documentviewer-6.0.3-py3.10-nspkg.pth
collective/documentviewer/CUSTOMIZATIONS.txt
collective/documentviewer/ISO-639-2_utf-8.txt
collective/documentviewer/__init__.py
collective/documentviewer/adapters.py
collective/documentviewer/async_utils.py
collective/documentviewer/catalog.py
collective/documentviewer/config.py
collective/documentviewer/configure.zcml
collective/documentviewer/convert.py
collective/documentviewer/convert_all.py
collective/documentviewer/events.py
collective/documentviewer/interfaces.py
collective/documentviewer/iso639_2_utf8.py
collective/documentviewer/migration.py
collective/documentviewer/settings.py
collective/documentviewer/setuphandlers.py
collective/documentviewer/storage.py
collective/documentviewer/subscribers.py
collective/documentviewer/testing.py
collective/documentviewer/upgrades.py
collective/documentviewer/upgrades.zcml
collective/documentviewer/utils.py
collective/documentviewer/browser/__init__.py
collective/documentviewer/browser/configure.zcml
collective/documentviewer/browser/controlpanel.py
collective/documentviewer/browser/settings.py
collective/documentviewer/browser/traverse.py
collective/documentviewer/browser/views.py
collective/documentviewer/browser/templates/async-monitor.pt
collective/documentviewer/browser/templates/converting.pt
collective/documentviewer/browser/templates/documentviewer.pt
collective/documentviewer/browser/templates/group-view.pt
collective/documentviewer/locales/collective.documentviewer-manual.pot
collective/documentviewer/locales/collective.documentviewer.pot
collective/documentviewer/locales/plone-manual.pot
collective/documentviewer/locales/plone.pot
collective/documentviewer/locales/rebuild_i18n.sh
collective/documentviewer/locales/de/LC_MESSAGES/collective.documentviewer.po
collective/documentviewer/locales/de/LC_MESSAGES/plone.po
collective/documentviewer/locales/en/LC_MESSAGES/collective.documentviewer.po
collective/documentviewer/locales/en/LC_MESSAGES/plone.po
collective.documentviewer-6.0.3.dist-info/METADATA
collective.documentviewer-6.0.3.dist-info/WHEEL
collective.documentviewer-6.0.3.dist-info/entry_points.txt
collective.documentviewer-6.0.3.dist-info/namespace_packages.txt
collective.documentviewer-6.0.3.dist-info/top_level.txt
collective.documentviewer-6.0.3.dist-info/RECORD
