Metadata-Version: 2.1
Name: collective.documentviewer
Version: 6.0.3
Summary: Document cloud's document viewer integration into plone.
Home-page: https://github.com/collective/collective.documentviewer
Author: Nathan Van Gheem
Author-email: vangheem@gmail.com
License: GPL
Keywords: plone documentviewer pdf ocr doc viewer
Classifier: Development Status :: 5 - Production/Stable
Classifier: Environment :: Web Environment
Classifier: Framework :: Plone
Classifier: Framework :: Plone :: Addon
Classifier: Framework :: Plone :: 5.0
Classifier: Framework :: Plone :: 5.1
Classifier: Framework :: Plone :: 5.2
Classifier: Framework :: Plone
Classifier: License :: OSI Approved :: GNU General Public License (GPL)
Classifier: Programming Language :: Python
Classifier: Programming Language :: Python :: 2.7
Classifier: Programming Language :: Python :: 3.7
Classifier: Programming Language :: Python :: 3.8
Classifier: Operating System :: OS Independent
Requires-Python: >=2.7,!=3.0.*,!=3.1.*,!=3.2.*,!=3.3.*,!=3.4.*,!=3.5.*
Requires-Dist: setuptools
Requires-Dist: plone.api
Requires-Dist: Products.CMFPlone
Requires-Dist: zope.browserresource
Requires-Dist: repoze.catalog (>=0.9.0)
Requires-Dist: plone.app.z3cform
Requires-Dist: collective.monkeypatcher
Requires-Dist: plone.app.contenttypes
Provides-Extra: test
Requires-Dist: plone.api ; extra == 'test'
Requires-Dist: plone.app.testing ; extra == 'test'
Requires-Dist: plone.testing ; extra == 'test'
Requires-Dist: plone.app.contenttypes ; extra == 'test'
Requires-Dist: collective.celery[test] ; extra == 'test'
